command_line_assistant/__init__.py
command_line_assistant/__main__.py
command_line_assistant-0.1.2.dist-info/licenses/LICENSE
command_line_assistant-0.1.2.dist-info/METADATA
command_line_assistant-0.1.2.dist-info/WHEEL
command_line_assistant-0.1.2.dist-info/entry_points.txt
command_line_assistant-0.1.2.dist-info/top_level.txt
command_line_assistant-0.1.2.dist-info/RECORD
