Metadata-Version: 2.4
Name: command-line-assistant
Version: 0.1.2
Summary: The command line assistant provides a natural language interface, and can incorporate information from resources such as the RHEL documentation.
Author-email: RHEL Lightspeed team <rhel-sst-lightspeed@redhat.com>
Maintainer-email: Rodolfo Olivieri <rolivier@redhat.com>, Major Hayden <mhayden@redhat.com>
License:                                  Apache License
Project-URL: Repository, https://github.com/rhel-lightspeed/command-line-assistant.git
Project-URL: Issues, https://github.com/rhel-lightspeed/command-line-assistant/issues
Classifier: Programming Language :: Python :: 3
Requires-Python: >=3.9
License-File: LICENSE
Dynamic: license-file
